sprockets.mixins.json_error-1.0.0-py2.7-nspkg.pth
sprockets/mixins/json_error/__init__.py
sprockets.mixins.json_error-1.0.0.dist-info/metadata.json
sprockets.mixins.json_error-1.0.0.dist-info/METADATA
sprockets.mixins.json_error-1.0.0.dist-info/WHEEL
sprockets.mixins.json_error-1.0.0.dist-info/namespace_packages.txt
sprockets.mixins.json_error-1.0.0.dist-info/DESCRIPTION.rst
sprockets.mixins.json_error-1.0.0.dist-info/RECORD
sprockets.mixins.json_error-1.0.0.dist-info/top_level.txt
