Metadata-Version: 2.0
Name: sprockets.mixins.json-error
Version: 1.0.0
Summary: Handler mixin for writing JSON errors
Home-page: https://github.com/sprockets/sprockets.mixins.json_error.git
Author: AWeber Communications
Author-email: api@aweber.com
License: Copyright (c) 2014 AWeber Communications
